aiogram_renderer/__init__.py
aiogram_renderer/bot_mode.py
aiogram_renderer/configure.py
aiogram_renderer/enums.py
aiogram_renderer/filters.py
aiogram_renderer/middlewares.py
aiogram_renderer/renderer.py
aiogram_renderer/window.py
aiogram_renderer/example/main.py
aiogram_renderer/example/routers.py
aiogram_renderer/example/states.py
aiogram_renderer/example/test.png
aiogram_renderer/example/windows.py
aiogram_renderer/handlers/inline_router.py
aiogram_renderer/handlers/reply_router.py
aiogram_renderer/widgets/__init__.py
aiogram_renderer/widgets/text.py
aiogram_renderer/widgets/widget.py
aiogram_renderer/widgets/inline/__init__.py
aiogram_renderer/widgets/inline/button.py
aiogram_renderer/widgets/inline/panel.py
aiogram_renderer/widgets/media/__init__.py
aiogram_renderer/widgets/media/bytes.py
aiogram_renderer/widgets/media/group.py
aiogram_renderer/widgets/media/path.py
aiogram_renderer/widgets/reply/__init__.py
aiogram_renderer/widgets/reply/button.py
aiogram_renderer/widgets/reply/panel.py
aiogram_renderer-1.3.7.dist-info/METADATA
aiogram_renderer-1.3.7.dist-info/WHEEL
aiogram_renderer-1.3.7.dist-info/licenses/LICENSE
aiogram_renderer-1.3.7.dist-info/RECORD
