Metadata-Version: 2.4
Name: aiogram-renderer
Version: 1.3.7
Summary: Библиотека UI-виджетов для Telegram-ботов с использованием aiogram3
Project-URL: Homepage, https://github.com/Foldren/aiogram-renderer
Project-URL: Issues, https://github.com/Foldren/aiogram-renderer/issues
Author: Foldren
License:                                  Apache License
License-File: LICENSE
Classifier: Intended Audience :: Developers
Classifier: License :: OSI Approved :: Apache Software License
Classifier: Operating System :: OS Independent
Classifier: Programming Language :: Python :: 3.9
Classifier: Programming Language :: Python :: 3.10
Classifier: Programming Language :: Python :: 3.11
Classifier: Programming Language :: Python :: 3.12
Classifier: Programming Language :: Python :: 3.13
Requires-Python: >=3.9
Requires-Dist: aiogram>=3.18.0
